{
    "title": "Steady Rowing",
    "ftmsMachineType": "DeviceDataType.rower",
    "intervals": [
        {
            "title": "Warm up",
            "duration": 30,
            "targets": {
                "Stroke Rate": 20,
                "Instantaneous Pace": "80%"
            },
            "resistanceLevel": 30
        },
        {
            "title": "Steady Rowing",
            "duration": 30,
            "targets": {
                "Stroke Rate": 24,
                "Instantaneous Pace": "100%"
            },
            "resistanceLevel": 60
        },
        {
            "title": "Cool Down",
            "duration": 30,
            "targets": {
                "Stroke Rate": 22,
                "Instantaneous Pace": "85%"
            },
            "resistanceLevel": 40
        }


    ]
}